{
    "AS_Button_d4aa40cfdffe4fb296a61be756f2845a": {
        "id": "AS_Button_d4aa40cfdffe4fb296a61be756f2845a",
        "type": "ACTION_SEQUENCE",
        "params": [{
            "datatype": "collection",
            "name": "eventobject"
        }, {
            "datatype": "string",
            "name": "x"
        }, {
            "datatype": "string",
            "name": "y"
        }],
        "contextObj": {
            "type": "forms",
            "platform": "",
            "KUID": "e0fc2dca561f4438b06a244012e51b5a"
        },
        "language": "js",
        "actions": [{
            "id": "INVOKE_FUNCTION___e7c54cb739db47ce82f7a3c8a2b25ff1",
            "type": "INVOKE_FUNCTION",
            "sequenceKUID": "login",
            "display": "login",
            "inputparams": [],
            "parentId": null,
            "callbackType": null,
            "disabled": null,
            "source": "module"
        }]
    }
}